{
    "homepage": "http://www.4yec.cn/",
    "version": "1.3.2.0",
    "license": "freeware",
    "url": "http://www.4yec.cn/download/CloverPdf_1.3.2.0.exe#/dl.7z",
    "hash": "3ddab0007f9e47215d033858304b03481e1f4de7256974cbedb3cdf5b43a17b8",
    "post_install": "Remove-Item \"$dir\\`$PLUGINSDIR\", \"$dir\\Uninstall.exe\" -Force -Recurse",
    "bin": "CloverPdf.exe",
    "shortcuts": [
        [
            "CloverPdf.exe",
            "CloverPdf"
        ]
    ],
    "checkver": "最新版本：([\\d.]+)",
    "autoupdate": {
        "url": "http://www.4yec.cn/download/CloverPdf_$version.exe#/dl.7z"
    }
}
