{
    "homepage": "https://kurtzimmermann.com",
    "version": "1.256",
    "license": "freeware",
    "architecture": {
        "64bit": {
            "url": "https://kurtzimmermann.com/files/HDCleanerX64.zip",
            "hash": "6e4ecedff6396697802b8ccbced1ef805ede675a9b2585a4192a9c9e1ed908a2"
        },
        "32bit": {
            "url": "https://kurtzimmermann.com/files/HDCleanerX32.zip",
            "hash": "a9f05471df3ade248412d9385c968a9ab50d2170564e76e36a6818f0056c90e1"
        }
    },
    "bin": "HDCleaner.exe",
    "persist": "Settings",
    "shortcuts": [
        [
            "HDCleaner.exe",
            "HDCleaner"
        ]
    ],
    "checkver": {
        "url": "https://kurtzimmermann.com/index_e.html",
        "re": "HDCleaner</h4>[\\w\\W]*?Version ([\\d\\.]+)"
    },
    "autoupdate": {
        "architecture": {
            "64bit": {
                "url": "https://kurtzimmermann.com/files/HDCleanerX64.zip"
            },
            "32bit": {
                "url": "https://kurtzimmermann.com/files/HDCleanerX32.zip"
            }
        }
    }
}
