{
    "homepage": "https://kurtzimmermann.com",
    "version": "1.114",
    "license": "freeware",
    "architecture": {
        "64bit": {
            "url": "https://kurtzimmermann.com/files/RegCoolX64.zip",
            "hash": "b192a6497347a86ec0b956b6e94a883ac0b610f23bb549ce88bc185919867b64"
        },
        "32bit": {
            "url": "https://kurtzimmermann.com/files/RegCoolX32.zip",
            "hash": "a15a17fd5b54573dc5319d034358a17d39ab541a15ed523a5fb99591acbd71de"
        }
    },
    "bin": "RegCool.exe",
    "persist": "Settings",
    "shortcuts": [
        [
            "RegCool.exe",
            "RegCool"
        ]
    ],
    "checkver": {
        "url": "https://kurtzimmermann.com/index_e.html",
        "regex": "RegCool</h4>[\\w\\W]*?Release notes:[\\w\\W]*?Version ([\\d.]+)"
    },
    "autoupdate": {
        "architecture": {
            "64bit": {
                "url": "https://kurtzimmermann.com/files/RegCoolX64.zip"
            },
            "32bit": {
                "url": "https://kurtzimmermann.com/files/RegCoolX32.zip"
            }
        }
    }
}
